{"на":3780,"по":2573,"ти":2548,"ли":2386,"ро":2366,"ст":2258,"ві":2098,"не":2070,"ов":2046,"та":1981,"го":1944,"ал":1920,"ко":1896,"ва":1894,"ер":1890,"ні":1838,"ор":1817,"ви":1797,"ра":1787,"ав":1765,"ог":1764,"ть":1757,"ка":1741,"во":1707,"но":1637,"за":1603,"до":1565,"ре":1563,"од":1555,"мо":1551,"ни":1529,"то":1528,"ся":1525,"ла":1444,"ат":1433,"ен":1408,"ом":1362,"ри":1362,"пр":1358,"ит":1341,"ло":1329,"ос":1322,"ма":1269,"ив":1259,"ки":1251,"ол":1228,"ан":1226,"тр":1161,"ін":1139,"ми":1134,"ди":1111,"чи":1092,"ід":1063,"ин":1055,"те":1050,"ів":1026,"іл":1018,"ис":1016,"об":1007,"ме":996,"ру":980,"ар":977,"он":960,"да":957,"ля":952,"що":950,"мі":936,"ам":918,"рі":904,"лі":883,"ил":882,"як":865,"ув":859,"бу":843,"ті":840,"ий":826,"ас":821,"ль":806,"им":796,"сь":791,"пе":787,"ба":760,"ле":760,"іт":752,"ок":749,"ку":744,"іс":741,"па":738,"ну":735,"кі":734,"от":726,"бо":710,"де":710,"пі":704,"вс":697,"му":695,"оч":692,"ді":691,"ак":687,"ає":677,"лю":673,"ду":664,"се":664,"ад":655,"оз":644,"ве":637,"аю":632,"хо":624,"га":621,"бі":595,"ьк":578,"аз":572,"ою":562,"их":559,"ої":548,"кр":547,"ій":547,"ці":547,"зн":546,"ча":543,"ай":541,"ня":540,"че":537,"же":534,"ик":534,"со":531,"си":526,"ул":516,"би":512,"ту":511,"дн":497,"це":496,"ьс":496,"ах":495,"бе":493,"ши":492,"ес":485,"ач":472,"ев":467,"ем":464,"ут":461,"ел":453,"ус":453,"сі":451,"ап":449,"пл":447,"ск":446,"ож":441,"йо":438,"нн":435,"уд":431,"аб":423,"нь":422,"ха":419,"пи":416,"ят":414,"св":398,"са":396,"ім":386,"чу":384,"ук":382,"ет":382,"бр":381,"жи":380,"оп":379,"сп":378,"ьо":375,"лу":372,"ум":372,"еб":371,"бл":370,"сл":348,"юч":345,"із":343,"ву":333,"ют":333,"аж":331,"гл":327,"ид":318,"ек":316,"сн":310,"зу":307,"рт":305,"ез":304,"вн":302,"ше":301,"чо":296,"др":293,"зв":290,"ед":288,"жн":287,"аг":286,"ир":285,"аш":277,"єт":274,"тя":270,"вш":270,"уб":269,"ір":265,"еп":260,"іч":260,"нк":260,"ей":257,"ря":256,"ік":253,"шо":253,"рн":243,"юд":241,"їх":237,"уж":236,"ич":236,"іш":234,"ох":233,"яв":231,"кл":230,"жа":229,"вл":227,"чі":222,"иш":222,"иг":222,"дв":222,"іб":219,"су":218,"ур":217,"еж":215,"зо":213,"мн":208,"гу":208,"ще":205,"жу":203,"нт":201,"ую":196,"ця":194,"ша":191,"вж":191,"уч":191,"см":189,"йш":185,"хв":185,"ьн":184,"пу":183,"зд":182,"тн":181,"ць":181,"гр":180,"шл":179,"іх":177,"ух":175,"дк":174,"хи":173,"вч":172,"її":169,"уп":168,"йн":167,"ег":166,"шу":165,"нц":163,"ує":162,"зе":161,"чн":160,"оя":159,"зі":152,"оє":150,"кт":150,"іг":149,"ке":148,"рш":147,"еч":145,"тв":145,"яд":144,"йс":142,"хт":142,"ян":141,"уг":141,"ги":139,"вт":139,"ун":139,"гн":136,"иц":135,"чк":135,"зя":134,"рк":134,"тк":133,"вк":132,"ип":132,"зм":131,"иб":130,"зр":129,"дл":129,"ац":128,"дя":128,"ой":128,"рм":127,"мл":126,"лк":126,"жі":124,"сц":123,"зи":122,"яч":122,"зп":122,"шт":120,"шк":120,"єм":118,"уш":118,"ял":117,"яг":116,"хн":114,"ху":113,"ія":112,"еш":112,"йт":111,"цю":111,"зл":111,"гі":109,"оф":109,"шн":109,"іж":109,"юв":108,"иж":107,"ію":107,"из":107,"тт":106,"жк":105,"йд":104,"рс":104,"фа":103,"кн":102,"їн":102,"іє":100,"ії":98,"юб":97,"зб":95,"фе":95,"ям":94,"ші":94,"бн":94,"зь":94,"ща":92,"нд":92,"жо":92,"гд":92,"фі":90,"вд":89,"вп":89,"дж":88,"ню":87,"нш":86,"яї":86,"зг":85,"вг":83,"дч":82,"дп":81,"ощ":81,"дс":80,"ге":80,"йа":80,"зк":79,"ец":79,"рю":78,"ош":77,"ях":76,"хі":76,"тл":76,"ьм":75,"рв":72,"йм":71,"дз":69,"уз":67,"яю":67,"юс":66,"дь":66,"фо":66,"щи":66,"шв":66,"чт":66,"ею":63,"мк":63,"вз":63,"еї":63,"рд":63,"єї":61,"йк":61,"яс":61,"хл":60,"єш":59,"яє":59,"ищ":59,"ьш":58,"нс":55,"ащ":55,"юм":55,"вр":54,"жч":54,"їт":54,"оц":54,"нч":54,"сх":54,"дд":53,"мб":53,"ює":53,"яз":52,"їм":52,"іц":51,"ех":49,"чч":49,"ци":49,"пт":49,"рб":49,"жл":48,"рг":47,"щі":47,"рц":47,"юю":47,"яр":47,"їй":46,"вм":46,"мп":45,"тю":42,"чя":40,"жд":40,"кв":40,"дц":40,"вв":39,"сю":39,"йц":39,"дб":38,"їз":37,"иї":37,"яж":37,"юн":36,"ьт":36,"бк":36,"хм":35,"аї":34,"ьг":34,"їд":34,"іа":33,"иє":33,"рл":33,"рх":32,"уя":32,"дм":32,"шп":32,"аф":31,"єю":31,"цн":31,"лл":31,"кс":29,"уй":29,"еа":29,"фр":29,"уц":29,"мр":28,"їв":28,"шм":28,"ца":27,"дт":27,"ея":27,"ьц":27,"рж":27,"щу":26,"ая":25,"іщ":25,"йб":25,"єц":25,"іп":24,"нз":24,"рч":24,"вщ":24,"хр":23,"гк":22,"нг":22,"дх":22,"ия":22,"уа":22,"вб":22,"пк":22,"ущ":21,"дш":21,"мт":21,"нє":21,"шх":21,"їж":20,"ющ":20,"ао":20,"йж":19,"гш":19,"зс":19,"пс":19,"гт":19,"зт":18,"єд":18,"рп":18,"яц":18,"юп":18,"сс":17,"иф":17,"зч":17,"вц":17,"вх":17,"ьй":17,"фу":17,"ео":16,"бс":16,"пн":16,"рь":16,"оо":16,"їс":16,"іо":15,"ау":15,"цу":15,"пц":15,"яш":14,"яй":13,"ьб":13,"тх":13,"шс":13,"юх":12,"бт":12,"цо":12,"ию":12,"їл":12,"йв":11,"еф":11,"уї":11,"кз":11,"дю":10,"вя":10,"юк":10,"ьв":10,"юр":10,"нр":10,"єн":10,"зх":10,"бв":10,"оа":10,"цт":9,"єк":9,"чц":9,"уо":9,"жб":9,"хе":9,"ещ":9,"фл":9,"дг":9,"мч":9,"кч":8,"нф":8,"фи":8,"чл":8,"яб":7,"пч":7,"рй":7,"зц":7,"йф":7,"гс":7,"ьф":7,"мв":6,"зш":6,"оі":6,"яп":6,"ґа":6,"тс":6,"єр":6,"юж":6,"бд":6,"цв":6,"бм":6,"єв":6,"шр":6,"мд":5,"юц":5,"сф":5,"юл":5,"кц":5,"гв":5,"бг":5,"їш":5,"чв":5,"бх":5,"мц":5,"пп":5,"мф":4,"ое":4,"йз":4,"лд":4,"тц":4,"дє":4,"єг":4,"кш":4,"зю":4,"цк":4,"зз":4,"тб":4,"ае":4,"юш":4,"чю":4,"жв":4,"шц":4,"ьє":3,"ґу":3,"сш":3,"ящ":3,"ья":3,"нщ":3,"тж":3,"іе":3,"іу":3,"йл":3,"лт":3,"бз":3,"кд":3,"кб":3,"мя":3,"жь":3,"уе":3,"яя":3,"жж":3,"юз":3,"шю":2,"фт":2,"рз":2,"пв":2,"єа":2,"рр":2,"тд":2,"ьщ":2,"ср":2,"нв":2,"бш":2,"нї":2,"жц":2,"юй":2,"ьї":2,"еі":2,"їі":2,"сє":2,"лс":2,"зж":2,"хс":2,"єс":2,"мш":2,"тм":2,"жя":2,"тч":2,"іь":2,"бп":2,"хк":2,"нл":2,"ґр":2,"йє":2,"єф":1,"фн":1,"зф":1,"юф":1,"йп":1,"пз":1,"ье":1,"тє":1,"ьп":1,"хг":1,"уу":1,"ее":1,"еє":1,"еу":1,"пш":1,"уф":1,"ии":1,"їч":1,"мм":1,"щй":1,"йю":1,"мг":1,"єх":1,"лг":1,"рє":1,"єз":1,"гз":1,"аі":1,"іі":1,"фс":1,"иґ":1,"цц":1,"їк":1,"йг":1,"щб":1,"шг":1,"тф":1,"ьд":1,"лм":1,"тш":1,"ьч":1,"яе":1,"лц":1,"яі":1,"юг":1,"бц":1,"єч":1,"мс":1,"шш":1,"пю":1,"бж":1,"хї":1,"їо":1,"щн":1,"чх":1,"кю":1,"яа":1,"лє":1,"єі":1,"пх":1,"бч":1,"йі":1,"єє":1,"иа":1,"лп":1,"мщ":1,"їи":1,"жт":1,"жм":1}